CHANGELOG.md
kibela_client/__init__.py
kibela_client/client.py
kibela_client/settings.py
kibela_client/types.py
kibela_client-0.1.0.dist-info/LICENSE
kibela_client-0.1.0.dist-info/WHEEL
kibela_client-0.1.0.dist-info/METADATA
kibela_client-0.1.0.dist-info/RECORD
